json_linter/__init__.py
json_linter/__main__.py
json_linter/config.py
json_linter/files.py
json_linter/linter.py
json_linter/main.py
json_linter/utils.py
json_linter/fixers/__init__.py
json_linter/fixers/sorted_keys.py
json_linter/rules/__init__.py
json_linter/rules/keys_are_sorted.py
json_linter/rules/naming_style_is_correct.py
tests/__init__.py
tests/linter_test.py
json_linter-1.3.0.dist-info/LICENSE
json_linter-1.3.0.dist-info/METADATA
json_linter-1.3.0.dist-info/WHEEL
json_linter-1.3.0.dist-info/entry_points.txt
json_linter-1.3.0.dist-info/top_level.txt
json_linter-1.3.0.dist-info/RECORD
