Metadata-Version: 2.1
Name: json-linter
Version: 1.3.0
Summary: Lint your JSON files!
Home-page: https://github.com/atomicptr/json-linter
Author: Christopher Kaster
Author-email: me@atomicptr.de
License: UNKNOWN
Platform: UNKNOWN
Classifier: Operating System :: OS Independent
Classifier: License :: OSI Approved :: GNU General Public License v3 (GPLv3)
Requires-Python: >=3.10
License-File: LICENSE
